ucuq/__init__.py
ucuq/ucuq.py
ucuq-0.1.1.dist-info/METADATA
ucuq-0.1.1.dist-info/WHEEL
ucuq-0.1.1.dist-info/top_level.txt
ucuq-0.1.1.dist-info/RECORD
