Metadata-Version: 2.1
Name: ucuq
Version: 0.1.1
Summary: A very light Python library with no dependencies for easy prototyping of projects based on Wi-Fi equipped microcontrollers (RPi Pico (2) W, ESP32, ESP8266…)
Home-page: https://github.com/epeios-q37/ucuq-python
Author: Claude SIMON
Keywords: microcontrolers,RPi Pico,ESP32,ESP8266,Wi-Fi,micropython,I2C,SPI,GPIO,PWM
Classifier: Development Status :: 5 - Production/Stable
Classifier: Environment :: Other Environment
Classifier: Intended Audience :: Developers
Classifier: Intended Audience :: Education
Classifier: Intended Audience :: Other Audience
Classifier: License :: OSI Approved :: MIT License
Classifier: Operating System :: OS Independent
Classifier: Operating System :: Other OS
Classifier: Programming Language :: Python :: 3
Classifier: Topic :: Internet
Classifier: Topic :: Scientific/Engineering
Classifier: Topic :: Software Development
Classifier: Topic :: Utilities
